context_compressor/__init__.py
context_compressor/cli.py
context_compressor/api/__init__.py
context_compressor/api/main.py
context_compressor/core/__init__.py
context_compressor/core/compressor.py
context_compressor/core/models.py
context_compressor/core/quality_evaluator.py
context_compressor/core/strategy_manager.py
context_compressor/integrations/__init__.py
context_compressor/integrations/langchain.py
context_compressor/integrations/openai.py
context_compressor/strategies/__init__.py
context_compressor/strategies/base.py
context_compressor/strategies/extractive.py
context_compressor/utils/__init__.py
context_compressor/utils/cache.py
context_compressor/utils/tokenizers.py
context_compressor-1.0.3.dist-info/licenses/LICENSE
context_compressor-1.0.3.dist-info/METADATA
context_compressor-1.0.3.dist-info/WHEEL
context_compressor-1.0.3.dist-info/entry_points.txt
context_compressor-1.0.3.dist-info/top_level.txt
context_compressor-1.0.3.dist-info/RECORD
