Metadata-Version: 2.4
Name: context-compressor
Version: 1.0.3
Summary: AI-powered text compression for RAG systems and API calls to reduce token usage and costs
Author-email: Mohammed Huzaifa <immdhuzaifa@gmail.com>
Maintainer-email: Mohammed Huzaifa <immdhuzaifa@gmail.com>
License: MIT
Project-URL: Homepage, https://github.com/Huzaifa785/context-compressor
Project-URL: Documentation, https://github.com/Huzaifa785/context-compressor#readme
Project-URL: Repository, https://github.com/Huzaifa785/context-compressor.git
Project-URL: Bug Tracker, https://github.com/Huzaifa785/context-compressor/issues
Project-URL: Changelog, https://github.com/Huzaifa785/context-compressor/blob/main/CHANGELOG.md
Keywords: ai,nlp,text-compression,rag,tokens,api-optimization,semantic-compression,llm
Classifier: Development Status :: 5 - Production/Stable
Classifier: Intended Audience :: Developers
Classifier: Intended Audience :: Science/Research
Classifier: License :: OSI Approved :: MIT License
Classifier: Operating System :: OS Independent
Classifier: Programming Language :: Python :: 3
Classifier: Programming Language :: Python :: 3.8
Classifier: Programming Language :: Python :: 3.9
Classifier: Programming Language :: Python :: 3.10
Classifier: Programming Language :: Python :: 3.11
Classifier: Programming Language :: Python :: 3.12
Classifier: Topic :: Scientific/Engineering :: Artificial Intelligence
Classifier: Topic :: Software Development :: Libraries :: Python Modules
Classifier: Topic :: Text Processing :: Linguistic
Requires-Python: >=3.8
License-File: LICENSE
Requires-Dist: numpy>=1.21.0
Requires-Dist: scikit-learn>=1.0.0
Requires-Dist: pydantic>=2.0.0
Requires-Dist: typing-extensions>=4.0.0
Requires-Dist: torch>=1.9.0
Requires-Dist: transformers>=4.20.0
Requires-Dist: sentence-transformers>=2.2.0
Requires-Dist: datasets>=2.0.0
Requires-Dist: fastapi>=0.100.0
Requires-Dist: uvicorn[standard]>=0.22.0
Requires-Dist: python-multipart>=0.0.6
Requires-Dist: langchain>=0.0.200
Requires-Dist: openai>=1.0.0
Requires-Dist: anthropic>=0.3.0
Requires-Dist: tiktoken>=0.4.0
Requires-Dist: spacy>=3.4.0
Requires-Dist: nltk>=3.8.0
Requires-Dist: textstat>=0.7.0
Requires-Dist: rouge-score>=0.1.2
Requires-Dist: scipy>=1.9.0
Requires-Dist: matplotlib>=3.5.0
Requires-Dist: seaborn>=0.11.0
Requires-Dist: plotly>=5.0.0
Requires-Dist: pandas>=1.5.0
Requires-Dist: tqdm>=4.64.0
Requires-Dist: joblib>=1.2.0
Provides-Extra: ml
Requires-Dist: torch>=1.9.0; extra == "ml"
Requires-Dist: transformers>=4.20.0; extra == "ml"
Requires-Dist: sentence-transformers>=2.2.0; extra == "ml"
Requires-Dist: datasets>=2.0.0; extra == "ml"
Provides-Extra: api
Requires-Dist: fastapi>=0.100.0; extra == "api"
Requires-Dist: uvicorn[standard]>=0.22.0; extra == "api"
Requires-Dist: python-multipart>=0.0.6; extra == "api"
Provides-Extra: integrations
Requires-Dist: langchain>=0.0.200; extra == "integrations"
Requires-Dist: openai>=1.0.0; extra == "integrations"
Requires-Dist: anthropic>=0.3.0; extra == "integrations"
Requires-Dist: tiktoken>=0.4.0; extra == "integrations"
Provides-Extra: nlp
Requires-Dist: spacy>=3.4.0; extra == "nlp"
Requires-Dist: nltk>=3.8.0; extra == "nlp"
Requires-Dist: textstat>=0.7.0; extra == "nlp"
Provides-Extra: dev
Requires-Dist: pytest>=7.0.0; extra == "dev"
Requires-Dist: pytest-cov>=4.0.0; extra == "dev"
Requires-Dist: pytest-mock>=3.10.0; extra == "dev"
Requires-Dist: pytest-asyncio>=0.21.0; extra == "dev"
Requires-Dist: black>=23.0.0; extra == "dev"
Requires-Dist: isort>=5.12.0; extra == "dev"
Requires-Dist: flake8>=6.0.0; extra == "dev"
Requires-Dist: mypy>=1.0.0; extra == "dev"
Requires-Dist: pre-commit>=3.0.0; extra == "dev"
Provides-Extra: docs
Requires-Dist: sphinx>=6.0.0; extra == "docs"
Requires-Dist: sphinx-rtd-theme>=1.2.0; extra == "docs"
Requires-Dist: sphinxcontrib-napoleon>=0.7; extra == "docs"
Requires-Dist: myst-parser>=1.0.0; extra == "docs"
Provides-Extra: all
Requires-Dist: context-compressor[api,integrations,ml,nlp]; extra == "all"
Provides-Extra: full
Requires-Dist: context-compressor[all,dev,docs]; extra == "full"
Dynamic: license-file
